flash_storage/__init__.py
flash_storage/cli.py
flash_storage/cloudinary_storage.py
flash_storage/config.py
flash_storage/flash.py
flash_storage/gdrive_storage.py
flash_storage/lfs_pointer.py
flash_storage/storage_manager.py
flash_storage/transfer_agent.py
flash_storage-0.3.0.dist-info/licenses/LICENSE
flash_storage-0.3.0.dist-info/METADATA
flash_storage-0.3.0.dist-info/WHEEL
flash_storage-0.3.0.dist-info/entry_points.txt
flash_storage-0.3.0.dist-info/top_level.txt
flash_storage-0.3.0.dist-info/RECORD
