Metadata-Version: 2.4
Name: flash-storage
Version: 0.3.0
Summary: Multi-cloud storage manager with automatic fallback for Git LFS (Cloudinary + Google Drive)
Author-email: Flash Storage Team <jonazjuan.dev@gmail.com>
License: MIT
Project-URL: Homepage, https://github.com/yourusername/flash-storage
Project-URL: Repository, https://github.com/yourusername/flash-storage
Keywords: git,lfs,cloudinary,google-drive,media,storage,cloud,backup
Classifier: Development Status :: 4 - Beta
Classifier: Intended Audience :: Developers
Classifier: License :: OSI Approved :: MIT License
Classifier: Programming Language :: Python :: 3
Classifier: Programming Language :: Python :: 3.8
Classifier: Programming Language :: Python :: 3.9
Classifier: Programming Language :: Python :: 3.10
Classifier: Programming Language :: Python :: 3.11
Classifier: Programming Language :: Python :: 3.12
Classifier: Programming Language :: Python :: 3.13
Requires-Python: >=3.8
License-File: LICENSE
Requires-Dist: cloudinary>=1.36.0
Requires-Dist: requests>=2.28.0
Requires-Dist: click>=8.1.0
Requires-Dist: python-dotenv>=1.0.0
Requires-Dist: google-auth>=2.16.0
Requires-Dist: google-auth-oauthlib>=1.0.0
Requires-Dist: google-auth-httplib2>=0.1.0
Requires-Dist: google-api-python-client>=2.80.0
Provides-Extra: dev
Requires-Dist: pytest>=7.0.0; extra == "dev"
Requires-Dist: black>=22.0.0; extra == "dev"
Requires-Dist: flake8>=5.0.0; extra == "dev"
Dynamic: license-file
